statelydb/__init__.py
statelydb/lib/__init__.py
statelydb/lib/api/__init__.py
statelydb/lib/api/auth/__init__.py
statelydb/lib/api/auth/get_auth_token_pb2.py
statelydb/lib/api/auth/get_auth_token_pb2.pyi
statelydb/lib/api/auth/service_grpc.py
statelydb/lib/api/auth/service_pb2.py
statelydb/lib/api/auth/service_pb2.pyi
statelydb/lib/api/db/__init__.py
statelydb/lib/api/db/continue_list_pb2.py
statelydb/lib/api/db/continue_list_pb2.pyi
statelydb/lib/api/db/continue_scan_pb2.py
statelydb/lib/api/db/continue_scan_pb2.pyi
statelydb/lib/api/db/delete_pb2.py
statelydb/lib/api/db/delete_pb2.pyi
statelydb/lib/api/db/get_pb2.py
statelydb/lib/api/db/get_pb2.pyi
statelydb/lib/api/db/item_pb2.py
statelydb/lib/api/db/item_pb2.pyi
statelydb/lib/api/db/list_filters_pb2.py
statelydb/lib/api/db/list_filters_pb2.pyi
statelydb/lib/api/db/list_pb2.py
statelydb/lib/api/db/list_pb2.pyi
statelydb/lib/api/db/list_token_pb2.py
statelydb/lib/api/db/list_token_pb2.pyi
statelydb/lib/api/db/put_pb2.py
statelydb/lib/api/db/put_pb2.pyi
statelydb/lib/api/db/scan_pb2.py
statelydb/lib/api/db/scan_pb2.pyi
statelydb/lib/api/db/service_grpc.py
statelydb/lib/api/db/service_pb2.py
statelydb/lib/api/db/service_pb2.pyi
statelydb/lib/api/db/sync_list_pb2.py
statelydb/lib/api/db/sync_list_pb2.pyi
statelydb/lib/api/db/transaction_pb2.py
statelydb/lib/api/db/transaction_pb2.pyi
statelydb/lib/api/errors/__init__.py
statelydb/lib/api/errors/error_details_pb2.py
statelydb/lib/api/errors/error_details_pb2.pyi
statelydb/py.typed
statelydb/src/__init__.py
statelydb/src/auth.py
statelydb/src/channel.py
statelydb/src/client.py
statelydb/src/errors.py
statelydb/src/keys.py
statelydb/src/list.py
statelydb/src/put_options.py
statelydb/src/stately_codes.py
statelydb/src/sync.py
statelydb/src/transaction.py
statelydb/src/types.py
statelydb-0.30.0.dist-info/LICENSE.txt
statelydb-0.30.0.dist-info/METADATA
statelydb-0.30.0.dist-info/WHEEL
statelydb-0.30.0.dist-info/RECORD
