Metadata-Version: 2.1
Name: statelydb
Version: 0.30.0
Summary: Python client for StatelyDB API
Home-page: https://stately.cloud
License: Apache-2.0
Keywords: stately,statelydb,statelycloud
Author: Stately Cloud
Author-email: support@stately.cloud
Requires-Python: >=3.9,<4.0
Classifier: License :: OSI Approved :: Apache Software License
Classifier: Programming Language :: Python :: 3
Classifier: Programming Language :: Python :: 3.9
Classifier: Programming Language :: Python :: 3.10
Classifier: Programming Language :: Python :: 3.11
Classifier: Programming Language :: Python :: 3.12
Classifier: Programming Language :: Python :: 3.13
Requires-Dist: aiohttp (>=3.11.11,<4.0.0)
Requires-Dist: googleapis-common-protos (>=1.65.0,<2.0.0)
Requires-Dist: grpclib (>=0.4.7,<0.5.0)
Requires-Dist: protobuf (>=6.0.0,<7.0.0)
Requires-Dist: typing-extensions (>=4.12.2,<5.0.0)
Project-URL: Documentation, https://docs.stately.cloud
Project-URL: Repository, https://github.com/StatelyCloud/python-sdk
